
{
  "header": {
    "reportVersion": 1,
    "event": "Allocation failed - JavaScript heap out of memory",
    "trigger": "FatalError",
    "filename": "report.20200708.122646.48808.0.001.json",
    "dumpEventTime": "2020-07-08T12:26:46Z",
    "dumpEventTimeStamp": "1594182406139",
    "processId": 48808,
    "cwd": "D:\\work\\CtgSuit",
    "commandLine": [
      "C:\\Program Files\\nodejs\\node.exe",
      "D:\\work\\CtgSuit\\node_modules\\umi\\lib\\scripts\\realDev.js",
      "dev"
    ],
    "nodejsVersion": "v12.16.1",
    "wordSize": 64,
    "arch": "x64",
    "platform": "win32",
    "componentVersions": {
      "node": "12.16.1",
      "v8": "7.8.279.23-node.31",
      "uv": "1.34.0",
      "zlib": "1.2.11",
      "brotli": "1.0.7",
      "ares": "1.15.0",
      "modules": "72",
      "nghttp2": "1.40.0",
      "napi": "5",
      "llhttp": "2.0.4",
      "http_parser": "2.9.3",
      "openssl": "1.1.1d",
      "cldr": "35.1",
      "icu": "64.2",
      "tz": "2019c",
      "unicode": "12.1"
    },
    "release": {
      "name": "node",
      "lts": "Erbium",
      "headersUrl": "https://nodejs.org/download/release/v12.16.1/node-v12.16.1-headers.tar.gz",
      "sourceUrl": "https://nodejs.org/download/release/v12.16.1/node-v12.16.1.tar.gz",
      "libUrl": "https://nodejs.org/download/release/v12.16.1/win-x64/node.lib"
    },
    "osName": "Windows_NT",
    "osRelease": "10.0.18363",
    "osVersion": "Windows 10 Home China",
    "osMachine": "x86_64",
    "cpus": [
      {
        "model": "Intel(R) Core(TM) i7-8550U CPU @ 1.80GHz",
        "speed": 1992,
        "user": 48780000,
        "nice": 0,
        "sys": 96490984,
        "idle": 445426953,
        "irq": 10616218
      },
      {
        "model": "Intel(R) Core(TM) i7-8550U CPU @ 1.80GHz",
        "speed": 1992,
        "user": 38361359,
        "nice": 0,
        "sys": 44737531,
        "idle": 507598218,
        "irq": 561656
      },
      {
        "model": "Intel(R) Core(TM) i7-8550U CPU @ 1.80GHz",
        "speed": 1992,
        "user": 71884203,
        "nice": 0,
        "sys": 63038765,
        "idle": 455774140,
        "irq": 1106515
      },
      {
        "model": "Intel(R) Core(TM) i7-8550U CPU @ 1.80GHz",
        "speed": 1992,
        "user": 56738828,
        "nice": 0,
        "sys": 67629843,
        "idle": 466328437,
        "irq": 758171
      },
      {
        "model": "Intel(R) Core(TM) i7-8550U CPU @ 1.80GHz",
        "speed": 1992,
        "user": 52320406,
        "nice": 0,
        "sys": 61577953,
        "idle": 476798750,
        "irq": 867953
      },
      {
        "model": "Intel(R) Core(TM) i7-8550U CPU @ 1.80GHz",
        "speed": 1992,
        "user": 40576750,
        "nice": 0,
        "sys": 69580078,
        "idle": 480540265,
        "irq": 705843
      },
      {
        "model": "Intel(R) Core(TM) i7-8550U CPU @ 1.80GHz",
        "speed": 1992,
        "user": 67090921,
        "nice": 0,
        "sys": 61567421,
        "idle": 462038750,
        "irq": 721328
      },
      {
        "model": "Intel(R) Core(TM) i7-8550U CPU @ 1.80GHz",
        "speed": 1992,
        "user": 77843203,
        "nice": 0,
        "sys": 70040703,
        "idle": 442813187,
        "irq": 625031
      }
    ],
    "networkInterfaces": [
      {
        "name": "以太网 3",
        "internal": false,
        "mac": "0a:00:27:00:00:08",
        "address": "fe80::de2:1a22:3b6f:a778",
        "netmask": "ffff:ffff:ffff:ffff::",
        "family": "IPv6",
        "scopeid": 8
      },
      {
        "name": "以太网 3",
        "internal": false,
        "mac": "0a:00:27:00:00:08",
        "address": "192.168.56.1",
        "netmask": "255.255.255.0",
        "family": "IPv4"
      },
      {
        "name": "VirtualBox Host-Only Network #3",
        "internal": false,
        "mac": "0a:00:27:00:00:10",
        "address": "fe80::90ec:aac5:2994:4a1",
        "netmask": "ffff:ffff:ffff:ffff::",
        "family": "IPv6",
        "scopeid": 16
      },
      {
        "name": "VirtualBox Host-Only Network #3",
        "internal": false,
        "mac": "0a:00:27:00:00:10",
        "address": "192.168.99.1",
        "netmask": "255.255.255.0",
        "family": "IPv4"
      },
      {
        "name": "WLAN",
        "internal": false,
        "mac": "d0:c6:37:2a:23:7b",
        "address": "fe80::4563:b712:c174:9284",
        "netmask": "ffff:ffff:ffff:ffff::",
        "family": "IPv6",
        "scopeid": 13
      },
      {
        "name": "WLAN",
        "internal": false,
        "mac": "d0:c6:37:2a:23:7b",
        "address": "192.168.123.48",
        "netmask": "255.255.255.0",
        "family": "IPv4"
      },
      {
        "name": "Loopback Pseudo-Interface 1",
        "internal": true,
        "mac": "00:00:00:00:00:00",
        "address": "::1",
        "netmask": "ffff:ffff:ffff:ffff:ffff:ffff:ffff:ffff",
        "family": "IPv6",
        "scopeid": 0
      },
      {
        "name": "Loopback Pseudo-Interface 1",
        "internal": true,
        "mac": "00:00:00:00:00:00",
        "address": "127.0.0.1",
        "netmask": "255.0.0.0",
        "family": "IPv4"
      }
    ],
    "host": "LAPTOP-2DGD985U"
  },
  "javascriptStack": {
    "message": "No stack.",
    "stack": [
      "Unavailable."
    ]
  },
  "nativeStack": [
    {
      "pc": "0x00007ff630b319f9",
      "symbol": ""
    },
    {
      "pc": "0x00007ff630b35e1c",
      "symbol": ""
    },
    {
      "pc": "0x00007ff630b34dd8",
      "symbol": ""
    },
    {
      "pc": "0x00007ff630c334cb",
      "symbol": ""
    },
    {
      "pc": "0x00007ff631449f4e",
      "symbol": ""
    },
    {
      "pc": "0x00007ff631432021",
      "symbol": ""
    },
    {
      "pc": "0x00007ff6312fe57c",
      "symbol": ""
    },
    {
      "pc": "0x00007ff631306521",
      "symbol": ""
    },
    {
      "pc": "0x00007ff6312fbb13",
      "symbol": ""
    },
    {
      "pc": "0x00007ff6312fa184",
      "symbol": ""
    },
    {
      "pc": "0x00007ff63131b36d",
      "symbol": ""
    },
    {
      "pc": "0x00007ff631080c51",
      "symbol": ""
    },
    {
      "pc": "0x00007ff631894ddd",
      "symbol": ""
    },
    {
      "pc": "0x00007ff631843cc6",
      "symbol": ""
    },
    {
      "pc": "0x00007ff6318f8f8b",
      "symbol": ""
    },
    {
      "pc": "0x00007ff631819d8c",
      "symbol": ""
    },
    {
      "pc": "0x000000451e550b6c",
      "symbol": ""
    }
  ],
  "javascriptHeap": {
    "totalMemory": 433033216,
    "totalCommittedMemory": 433033216,
    "usedMemory": 423113144,
    "availableMemory": 1773593296,
    "memoryLimit": 2197815296,
    "heapSpaces": {
      "read_only_space": {
        "memorySize": 262144,
        "committedMemory": 262144,
        "capacity": 32808,
        "used": 32808,
        "available": 0
      },
      "new_space": {
        "memorySize": 1048576,
        "committedMemory": 1048576,
        "capacity": 1047456,
        "used": 1047448,
        "available": 8
      },
      "old_space": {
        "memorySize": 209862656,
        "committedMemory": 209862656,
        "capacity": 208573672,
        "used": 208037680,
        "available": 535992
      },
      "code_space": {
        "memorySize": 4362240,
        "committedMemory": 4362240,
        "capacity": 4104512,
        "used": 3885600,
        "available": 218912
      },
      "map_space": {
        "memorySize": 11538432,
        "committedMemory": 11538432,
        "capacity": 11525328,
        "used": 4516480,
        "available": 7008848
      },
      "large_object_space": {
        "memorySize": 205336576,
        "committedMemory": 205336576,
        "capacity": 205048840,
        "used": 205048840,
        "available": 0
      },
      "code_large_object_space": {
        "memorySize": 622592,
        "committedMemory": 622592,
        "capacity": 544288,
        "used": 544288,
        "available": 0
      },
      "new_large_object_space": {
        "memorySize": 0,
        "committedMemory": 0,
        "capacity": 1047456,
        "used": 0,
        "available": 1047456
      }
    }
  },
  "resourceUsage": {
    "userCpuSeconds": 677.484,
    "kernelCpuSeconds": 171.906,
    "cpuConsumptionPercent": 1.16473,
    "maxRss": 1195876352,
    "pageFaults": {
      "IORequired": 5545011,
      "IONotRequired": 0
    },
    "fsActivity": {
      "reads": 35042,
      "writes": 120
    }
  },
  "libuv": [
  ],
  "environmentVariables": {
    "=D:": "D:\\work\\CtgSuit",
    "ALLUSERSPROFILE": "C:\\ProgramData",
    "APPDATA": "C:\\Users\\lianmed\\AppData\\Roaming",
    "ChocolateyInstall": "C:\\ProgramData\\chocolatey",
    "ChocolateyLastPathUpdate": "132160539808599055",
    "CLASSPATH": ".;C:\\Program Files\\Java\\jdk1.8.0_212\\lib\\dt.jar;C:\\Program Files\\Java\\jdk1.8.0_212\\lib\\tools.jar;",
    "CODE_SPLITTING_LEVEL": "3",
    "CommonProgramFiles": "C:\\Program Files\\Common Files",
    "CommonProgramFiles(x86)": "C:\\Program Files (x86)\\Common Files",
    "CommonProgramW6432": "C:\\Program Files\\Common Files",
    "COMPOSE_CONVERT_WINDOWS_PATHS": "true",
    "COMPUTERNAME": "LAPTOP-2DGD985U",
    "ComSpec": "C:\\WINDOWS\\system32\\cmd.exe",
    "DOCKER_CERT_PATH": "C:\\Users\\lianmed\\.docker\\machine\\machines\\default",
    "DOCKER_HOST": "tcp://192.168.99.100:2376",
    "DOCKER_MACHINE_NAME": "default",
    "DOCKER_TLS_VERIFY": "1",
    "DriverData": "C:\\Windows\\System32\\Drivers\\DriverData",
    "ESLINT": "1",
    "GROOVY_HOME": "d:\\Program Files\\groovy-3.0.2",
    "HOMEDRIVE": "C:",
    "HOMEPATH": "\\Users\\lianmed",
    "INIT_CWD": "D:\\work\\CtgSuit",
    "IntelliJ IDEA": "C:\\Program Files\\JetBrains\\IntelliJ IDEA 2019.3.3\\bin;",
    "JAVA_HOME": "C:\\Program Files\\Java\\jdk1.8.0_212",
    "LOCALAPPDATA": "C:\\Users\\lianmed\\AppData\\Local",
    "LOGONSERVER": "\\\\LAPTOP-2DGD985U",
    "MAVEN_HOME": "D:\\Program Files\\apache-maven-3.6.3",
    "NODE": "C:\\Program Files\\nodejs\\node.exe",
    "NODE_ENV": "development",
    "NO_PROXY": "192.168.99.100",
    "npm_config_argv": "{\"remain\":[],\"cooked\":[\"run\",\"start:render\"],\"original\":[\"start:render\"]}",
    "npm_config_bin_links": "true",
    "npm_config_ignore_optional": "",
    "npm_config_ignore_scripts": "",
    "npm_config_init_license": "MIT",
    "npm_config_init_version": "1.0.0",
    "npm_config_registry": "https://registry.yarnpkg.com",
    "npm_config_save_prefix": "^",
    "npm_config_strict_ssl": "true",
    "npm_config_user_agent": "yarn/1.16.0 npm/? node/v12.16.1 win32 x64",
    "npm_config_version_commit_hooks": "true",
    "npm_config_version_git_message": "v%s",
    "npm_config_version_git_sign": "",
    "npm_config_version_git_tag": "true",
    "npm_config_version_tag_prefix": "v",
    "npm_execpath": "C:\\Program Files (x86)\\Yarn\\bin\\yarn.js",
    "npm_lifecycle_event": "start:render",
    "npm_lifecycle_script": "cross-env PORT=1702 TARGET=0 umi dev",
    "npm_node_execpath": "C:\\Program Files\\nodejs\\node.exe",
    "npm_package_author_email": "lian-med@163.com",
    "npm_package_author_name": "Lian-Med",
    "npm_package_build_appId": "lian-med-ctgsuit",
    "npm_package_build_asar": "true",
    "npm_package_build_compression": "maximum",
    "npm_package_build_copyright": "Copyright © 2019 lian-med",
    "npm_package_build_directories_output": "release",
    "npm_package_build_linux_category": "Development",
    "npm_package_build_linux_target_0": "snap",
    "npm_package_build_linux_target_1": "AppImage",
    "npm_package_build_mac_target_0": "dmg",
    "npm_package_build_mac_target_1": "zip",
    "npm_package_build_nsis_allowElevation": "true",
    "npm_package_build_nsis_allowToChangeInstallationDirectory": "true",
    "npm_package_build_nsis_menuCategory": "true",
    "npm_package_build_nsis_oneClick": "false",
    "npm_package_build_productName": "ObVue",
    "npm_package_build_win_icon": "build/icon.ico",
    "npm_package_build_win_target_0": "nsis",
    "npm_package_build_win_target_1": "zip",
    "npm_package_dependencies_antd": "^4.0.0-rc.5",
    "npm_package_dependencies_bezier_easing": "^2.1.0",
    "npm_package_dependencies_braft_editor": "^2.3.8",
    "npm_package_dependencies_braft_utils": "^3.0.12",
    "npm_package_dependencies_dva": "^2.6.0-beta.6",
    "npm_package_dependencies_qrcode": "^1.4.4",
    "npm_package_dependencies_ramda": "^0.26.1",
    "npm_package_dependencies_react": "^16.8.6",
    "npm_package_dependencies_react_color": "^2.17.3",
    "npm_package_dependencies_react_dom": "^16.8.6",
    "npm_package_dependencies_react_highlight_words": "^0.16.0",
    "npm_package_dependencies_react_pdf": "^4.1.0",
    "npm_package_dependencies_store": "^2.0.12",
    "npm_package_dependencies_styled_components": "^5.0.1",
    "npm_package_dependencies_umi_request": "^1.2.2",
    "npm_package_dependencies__ant_design_compatible": "^0.0.1-rc.1",
    "npm_package_dependencies__ant_design_icons": "^4.0.0",
    "npm_package_description": "Electron example with [umi](https://github.com/umijs/umi/) ## 目录说明 ```bash",
    "npm_package_devDependencies_asar": "^2.0.3",
    "npm_package_devDependencies_babel_eslint": "^9.0.0",
    "npm_package_devDependencies_compressing": "^1.5.0",
    "npm_package_devDependencies_concurrently": "^4.1.2",
    "npm_package_devDependencies_cross_env": "^6.0.0",
    "npm_package_devDependencies_electron": "^5.0.13",
    "npm_package_devDependencies_electron_builder": "^21.1.5",
    "npm_package_devDependencies_electron_is_dev": "^1.1.0",
    "npm_package_devDependencies_electron_rebuild": "^1.8.5",
    "npm_package_devDependencies_electron_store": "^5.0.0",
    "npm_package_devDependencies_eslint": "^5.4.0",
    "npm_package_devDependencies_eslint_config_umi": "^1.4.0",
    "npm_package_devDependencies_eslint_plugin_flowtype": "^2.50.0",
    "npm_package_devDependencies_eslint_plugin_import": "^2.14.0",
    "npm_package_devDependencies_eslint_plugin_jsx_a11y": "^5.1.1",
    "npm_package_devDependencies_eslint_plugin_react": "^7.11.1",
    "npm_package_devDependencies_glob": "^7.1.6",
    "npm_package_devDependencies_gulp": "^4.0.2",
    "npm_package_devDependencies_gulp_typescript": "^6.0.0-alpha.1",
    "npm_package_devDependencies_gulp_uglyfly": "^1.4.2",
    "npm_package_devDependencies_husky": "^0.14.3",
    "npm_package_devDependencies_lint_staged": "^7.2.2",
    "npm_package_devDependencies_mockjs": "^1.0.1-beta3",
    "npm_package_devDependencies_postcss_px_to_viewport": "^1.1.1",
    "npm_package_devDependencies_progress": "^2.0.3",
    "npm_package_devDependencies_react_test_renderer": "^16.7.0",
    "npm_package_devDependencies_roadhog_api_doc": "^1.1.2",
    "npm_package_devDependencies_run_electron": "^1.0.0",
    "npm_package_devDependencies_shx": "^0.3.2",
    "npm_package_devDependencies_slash": "^3.0.0",
    "npm_package_devDependencies_ts_node": "^8.5.4",
    "npm_package_devDependencies_umi": "^2.7.7",
    "npm_package_devDependencies_umi_plugin_react": "^1.8.4",
    "npm_package_devDependencies_webpack": "^4.41.0",
    "npm_package_devDependencies_webpack_chain": "^6.0.0",
    "npm_package_devDependencies_yargs_parser": "^16.1.0",
    "npm_package_devDependencies__chatie_tsconfig": "^0.6.1",
    "npm_package_devDependencies__types_dotenv": "^8.2.0",
    "npm_package_devDependencies__types_gulp": "^4.0.6",
    "npm_package_devDependencies__types_gulp_typescript": "^2.13.0",
    "npm_package_devDependencies__types_lodash": "^4.14.144",
    "npm_package_devDependencies__types_request": "^2.48.3",
    "npm_package_devDependencies__types_webpack": "^4.41.2",
    "npm_package_engines_node": ">=8.0.0",
    "npm_package_license": "lianmed-1.0.0",
    "npm_package_lint_staged____js_jsx__0": "eslint --fix",
    "npm_package_lint_staged____js_jsx__1": "git add",
    "npm_package_main": "./app/main/index.js",
    "npm_package_name": "ctg-suit",
    "npm_package_private": "true",
    "npm_package_readmeFilename": "README.md",
    "npm_package_scripts_build": "ts-node --project main/tsconfig.json ./scripts/build",
    "npm_package_scripts_build_main": "tsc --project ./app/tsconfig.json",
    "npm_package_scripts_build_render": "cross-env BROWSER=none umi build",
    "npm_package_scripts_build_runtime": "umi build",
    "npm_package_scripts_codepush_browser": "node ./scripts/codepush.js --dir=.tmp  --base app --target=browser",
    "npm_package_scripts_codepush_desktop": "node ./scripts/codepush.js --dir=.tmp  --base=app --target=desktop",
    "npm_package_scripts_deploy_browser": "yarn vh && yarn gulp && yarn build:runtime && yarn codepush:browser",
    "npm_package_scripts_deploy_desktop": "yarn vh && yarn gulp  && yarn build:render && yarn codepush:desktop && explorer .tmp",
    "npm_package_scripts_dev_main": "yarn gulp && run-electron .",
    "npm_package_scripts_dist": "electron-builder",
    "npm_package_scripts_dist_ia32": "electron-builder --ia32",
    "npm_package_scripts_gulp": "gulp --silent",
    "npm_package_scripts_link_lianmed": "npm link @lianmed/lmg @lianmed/components @lianmed/utils @lianmed/request @lianmed/pages",
    "npm_package_scripts_lint": "eslint --ext .js src mock tests",
    "npm_package_scripts_pack": "npm run build:render && npm run rebuild && electron-builder --dir =./app",
    "npm_package_scripts_pack_ia32": "npm run build:render && npm run rebuild && electron-builder  --ia32 --dir =./app",
    "npm_package_scripts_pack_linux": "npm run build:render && npm run rebuild && electron-builder build --linux",
    "npm_package_scripts_pp": "electron-builder --dir =./app",
    "npm_package_scripts_precommit": "lint-staged",
    "npm_package_scripts_rebuild": "electron-rebuild -m ./app",
    "npm_package_scripts_start": "cross-env PORT=1702 BROWSER=none umi dev",
    "npm_package_scripts_start_dev": "concurrently  'yarn start' 'yarn run dev:main'",
    "npm_package_scripts_start_main": "run-electron .",
    "npm_package_scripts_start_render": "cross-env PORT=1702 TARGET=0 umi dev",
    "npm_package_scripts_test": "umi test",
    "npm_package_scripts_update_lianmed": "yarn upgrade @lianmed/lmg @lianmed/components @lianmed/utils @lianmed/request",
    "npm_package_scripts_vh": "ts-node --project ./main/tsconfig.json ./scripts/versionHandler ",
    "npm_package_scripts__deploy_desktop": "yarn vh && yarn gulp  && yarn codepush:desktop",
    "npm_package_scripts__dev_main": "wsl make && run-electron .",
    "npm_package_version": "1.12.10",
    "NUMBER_OF_PROCESSORS": "8",
    "NVM_HOME": "C:\\Users\\lianmed\\AppData\\Roaming\\nvm",
    "NVM_SYMLINK": "C:\\Program Files\\nodejs",
    "OneDrive": "C:\\Users\\lianmed\\OneDrive",
    "OS": "Windows_NT",
    "Path": "C:\\Users\\lianmed\\AppData\\Local\\Temp\\yarn--1594109475191-0.5349657008427888;D:\\work\\CtgSuit\\node_modules\\.bin;C:\\Users\\lianmed\\AppData\\Local\\Yarn\\Data\\link\\node_modules\\.bin;C:\\Program Files\\libexec\\lib\\node_modules\\npm\\bin\\node-gyp-bin;C:\\Program Files\\lib\\node_modules\\npm\\bin\\node-gyp-bin;C:\\Program Files\\nodejs\\node_modules\\npm\\bin\\node-gyp-bin;C:\\Program Files\\Java\\jdk1.8.0_212\\bin;C:\\Program Files\\Java\\jdk1.8.0_212\\jre\\bin;C:\\Program Files (x86)\\Yarn\\bin\\;C:\\Windows\\system32;C:\\Windows;C:\\Program Files (x86)\\Intel\\Intel(R) Management Engine Components\\iCLS\\;C:\\Program Files\\Intel\\Intel(R) Management Engine Components\\iCLS\\;C:\\Windows\\System32\\Wbem;C:\\Windows\\System32\\WindowsPowerShell\\v1.0\\;C:\\Windows\\System32\\OpenSSH\\;D:\\Program Files\\apache-maven-3.6.3\\bin;C:\\Program Files (x86)\\Intel\\Intel(R) Management Engine Components\\DAL;C:\\Program Files\\Intel\\Intel(R) Management Engine Components\\DAL;C:\\Program Files\\Intel\\WiFi\\bin\\;C:\\Program Files\\Common Files\\Intel\\WirelessCommon\\;C:\\Program Files (x86)\\NVIDIA Corporation\\PhysX\\Common;C:\\Program Files\\NVIDIA Corporation\\NVIDIA NvDLISR;C:\\Program Files\\Git\\cmd;C:\\WINDOWS\\system32;C:\\WINDOWS;C:\\WINDOWS\\System32\\Wbem;C:\\WINDOWS\\System32\\WindowsPowerShell\\v1.0\\;C:\\WINDOWS\\System32\\OpenSSH\\;C:\\Program Files\\Microsoft SQL Server\\130\\Tools\\Binn\\;?C:\\Program Files\\Git\\usr\\bin\\mintty.exe;C:\\Program Files\\TortoiseSVN\\bin;d:\\Program Files\\groovy-3.0.2\\bin;C:\\Users\\lianmed\\AppData\\Roaming\\nvm;C:\\Program Files\\nodejs;C:\\Program Files\\Microsoft SQL Server\\Client SDK\\ODBC\\170\\Tools\\Binn\\;C:\\Program Files\\dotnet\\;C:\\Program Files\\NASM;C:\\Program Files\\MySQL\\MySQL Shell 8.0\\bin\\;C:\\Users\\lianmed\\.poetry\\bin;C:\\Users\\lianmed\\scoop\\shims;C:\\Users\\lianmed\\AppData\\Local\\Microsoft\\WindowsApps;C:\\Users\\lianmed\\AppData\\Roaming\\npm;C:\\Users\\lianmed\\AppData\\Local\\Programs\\Microsoft VS Code\\bin;C:\\Users\\lianmed\\AppData\\Local\\Yarn\\bin;D:\\downloads\\wsl-terminal-0.8.13\\wsl-terminal;C:\\Program Files (x86)\\CMake\\bin;C:\\Program Files\\JetBrains\\IntelliJ IDEA 2019.3.3\\bin;C:\\Users\\lianmed\\.dotnet\\tools",
    "PATHEXT": ".COM;.EXE;.BAT;.CMD;.VBS;.VBE;.JSE;.WSF;.WSH;.MSC;.CPL",
    "PORT": "1702",
    "PROCESSOR_ARCHITECTURE": "AMD64",
    "PROCESSOR_IDENTIFIER": "Intel64 Family 6 Model 142 Stepping 10, GenuineIntel",
    "PROCESSOR_LEVEL": "6",
    "PROCESSOR_REVISION": "8e0a",
    "ProgramData": "C:\\ProgramData",
    "ProgramFiles": "C:\\Program Files",
    "ProgramFiles(x86)": "C:\\Program Files (x86)",
    "ProgramW6432": "C:\\Program Files",
    "PROMPT": "$P$G",
    "PSModulePath": "C:\\Users\\lianmed\\Documents\\WindowsPowerShell\\Modules;C:\\Program Files\\WindowsPowerShell\\Modules;C:\\WINDOWS\\system32\\WindowsPowerShell\\v1.0\\Modules",
    "PUBLIC": "C:\\Users\\Public",
    "SystemDrive": "C:",
    "SystemRoot": "C:\\WINDOWS",
    "TARGET": "0",
    "TEMP": "C:\\Users\\lianmed\\AppData\\Local\\Temp",
    "TMP": "C:\\Users\\lianmed\\AppData\\Local\\Temp",
    "UMI_DIR": "D:\\work\\CtgSuit\\node_modules\\umi",
    "UMI_UI": "none",
    "UMI_VERSION": "2.13.0",
    "USERDOMAIN": "LAPTOP-2DGD985U",
    "USERDOMAIN_ROAMINGPROFILE": "LAPTOP-2DGD985U",
    "USERNAME": "lianmed",
    "USERPROFILE": "C:\\Users\\lianmed",
    "VBOX_MSI_INSTALL_PATH": "C:\\Program Files\\Oracle\\VirtualBox\\",
    "VS160ENTCOMNTOOLS": "C:\\Program Files (x86)\\Microsoft Visual Studio\\2019\\Enterprise\\Common7\\Tools\\",
    "windir": "C:\\WINDOWS",
    "WSLENV": "WT_SESSION::WT_PROFILE_ID",
    "WT_PROFILE_ID": "{61c54bbd-c2c6-5271-96e7-009a87ff44bf}",
    "WT_SESSION": "c89dc9c7-ea3b-48bb-b715-860a679abc08",
    "YARN_WRAP_OUTPUT": "false",
    "_REMOTE": "",
    "_SONGJIAN": "22"
  },
  "sharedObjects": [
    "C:\\Program Files\\nodejs\\node.exe",
    "C:\\WINDOWS\\SYSTEM32\\ntdll.dll",
    "C:\\WINDOWS\\System32\\KERNEL32.DLL",
    "C:\\WINDOWS\\System32\\KERNELBASE.dll",
    "C:\\WINDOWS\\System32\\WS2_32.dll",
    "C:\\WINDOWS\\System32\\RPCRT4.dll",
    "C:\\WINDOWS\\System32\\PSAPI.DLL",
    "C:\\WINDOWS\\System32\\ADVAPI32.dll",
    "C:\\WINDOWS\\System32\\msvcrt.dll",
    "C:\\WINDOWS\\System32\\sechost.dll",
    "C:\\WINDOWS\\System32\\USER32.dll",
    "C:\\WINDOWS\\System32\\win32u.dll",
    "C:\\WINDOWS\\System32\\GDI32.dll",
    "C:\\WINDOWS\\System32\\gdi32full.dll",
    "C:\\WINDOWS\\System32\\msvcp_win.dll",
    "C:\\WINDOWS\\System32\\ucrtbase.dll",
    "C:\\WINDOWS\\System32\\CRYPT32.dll",
    "C:\\WINDOWS\\System32\\MSASN1.dll",
    "C:\\WINDOWS\\System32\\bcrypt.dll",
    "C:\\WINDOWS\\SYSTEM32\\dbghelp.dll",
    "C:\\WINDOWS\\SYSTEM32\\IPHLPAPI.DLL",
    "C:\\WINDOWS\\SYSTEM32\\USERENV.dll",
    "C:\\WINDOWS\\System32\\profapi.dll",
    "C:\\WINDOWS\\SYSTEM32\\WINMM.dll",
    "C:\\WINDOWS\\SYSTEM32\\WINMMBASE.dll",
    "C:\\WINDOWS\\System32\\cfgmgr32.dll",
    "C:\\WINDOWS\\System32\\bcryptPrimitives.dll",
    "C:\\WINDOWS\\System32\\IMM32.DLL",
    "C:\\WINDOWS\\System32\\powrprof.dll",
    "C:\\WINDOWS\\System32\\UMPDC.dll",
    "C:\\WINDOWS\\SYSTEM32\\CRYPTBASE.DLL",
    "C:\\WINDOWS\\system32\\uxtheme.dll",
    "C:\\WINDOWS\\System32\\combase.dll",
    "C:\\WINDOWS\\system32\\mswsock.dll",
    "C:\\WINDOWS\\System32\\kernel.appcore.dll",
    "C:\\WINDOWS\\System32\\NSI.dll",
    "C:\\WINDOWS\\SYSTEM32\\dhcpcsvc6.DLL",
    "C:\\WINDOWS\\SYSTEM32\\dhcpcsvc.DLL",
    "C:\\WINDOWS\\SYSTEM32\\DNSAPI.dll",
    "C:\\WINDOWS\\system32\\napinsp.dll",
    "C:\\WINDOWS\\system32\\pnrpnsp.dll",
    "C:\\WINDOWS\\System32\\winrnr.dll",
    "C:\\WINDOWS\\system32\\NLAapi.dll",
    "C:\\WINDOWS\\system32\\wshbth.dll"
  ]
}